scripts/comparisons.py
tufteplotlib/__init__.py
tufteplotlib/styles.py
tufteplotlib/utils.py
tufteplotlib/datasets/__init__.py
tufteplotlib/datasets/anscombe.py
tufteplotlib/plots/__init__.py
tufteplotlib/plots/bar.py
tufteplotlib/plots/barcode.py
tufteplotlib/plots/column.py
tufteplotlib/plots/density.py
tufteplotlib/plots/galaxy.py
tufteplotlib/plots/histogram.py
tufteplotlib/plots/line.py
tufteplotlib/plots/pareto.py
tufteplotlib/plots/quartile.py
tufteplotlib/plots/rug.py
tufteplotlib/plots/scatter.py
tufteplotlib/plots/sparkline.py
tufteplotlib/plots/stem_and_leaf.py
tufteplotlib/plots/time.py
tufteplotlib-1.1.0.dist-info/licenses/LICENSE
tufteplotlib-1.1.0.dist-info/METADATA
tufteplotlib-1.1.0.dist-info/WHEEL
tufteplotlib-1.1.0.dist-info/entry_points.txt
tufteplotlib-1.1.0.dist-info/top_level.txt
tufteplotlib-1.1.0.dist-info/RECORD
