Metadata-Version: 2.4
Name: tufteplotlib
Version: 1.1.0
Summary: An extension to matplotlib for creating graphs in the style of Edward Tufte.
Home-page: https://github.com/Woolfrey/software_tufte_plot
Author: Jon Woolfrey
Author-email: Jon Woolfrey <jonathan.woolfrey@gmail.com>
License: GPLv3
Project-URL: Homepage, https://github.com/Woolfrey/software_tufte_plot
Project-URL: Source, https://github.com/Woolfrey/software_tufte_plot
Project-URL: Bug Reports, https://github.com/Woolfrey/software_tufte_plot/issues
Keywords: matplotlib,tufte,visualization,plotting,minimalistic,graph
Requires-Python: >=3.10
License-File: LICENSE
Requires-Dist: matplotlib>=3.0
Requires-Dist: numpy>=1.21
Requires-Dist: pandas>=1.4
Dynamic: author
Dynamic: home-page
Dynamic: license-file
Dynamic: requires-python
